{
  "$schema": "https://aka.ms/winget-packages.schema.2.0.json",
  "CreationDate": "2025-04-10T08:29:20.092-00:00",
  "Sources": [
    {
      "Packages": [
        {
          "PackageIdentifier": "7zip.7zip"
        },
        {
          "PackageIdentifier": "Git.Git"
        },
        {
          "PackageIdentifier": "KiCad.KiCad"
        },
        {
          "PackageIdentifier": "Mozilla.Firefox"
        },
        {
          "PackageIdentifier": "Cloudflare.Warp"
        },
        {
          "PackageIdentifier": "Inkscape.Inkscape"
        },
        {
          "PackageIdentifier": "RealVNC.VNCViewer"
        },
        {
          "PackageIdentifier": "TheDocumentFoundation.LibreOffice"
        },
        {
          "PackageIdentifier": "dorssel.usbipd-win"
        },
        {
          "PackageIdentifier": "WinSCP.WinSCP"
        },
        {
          "PackageIdentifier": "PuTTY.PuTTY"
        },
        {
          "PackageIdentifier": "Python.Launcher"
        },
        {
          "PackageIdentifier": "Famatech.AdvancedIPScanner"
        },
        {
          "PackageIdentifier": "Google.CloudSDK"
        },
        {
          "PackageIdentifier": "RaspberryPiFoundation.RaspberryPiImager"
        },
        {
          "PackageIdentifier": "Python.Python.3.11"
        },
        {
          "PackageIdentifier": "Microsoft.VisualStudioCode"
        },
        {
          "PackageIdentifier": "Microsoft.AppInstaller"
        },
        {
          "PackageIdentifier": "Microsoft.WindowsTerminal"
        },
        {
          "PackageIdentifier": "Microsoft.WSL"
        }
      ],
      "SourceDetails": {
        "Argument": "https://cdn.winget.microsoft.com/cache",
        "Identifier": "Microsoft.Winget.Source_8wekyb3d8bbwe",
        "Name": "winget",
        "Type": "Microsoft.PreIndexed.Package"
      }
    }
  ],
  "WinGetVersion": "1.10.340"
}
